README.rst
setup.cfg
setup.py
django_quiet_runserver.egg-info/PKG-INFO
django_quiet_runserver.egg-info/SOURCES.txt
django_quiet_runserver.egg-info/dependency_links.txt
django_quiet_runserver.egg-info/requires.txt
django_quiet_runserver.egg-info/top_level.txt
django_quiet_runserver.egg-info/zip-safe
djangoquietrunserver/__init__.py
djangoquietrunserver/apps.py
djangoquietrunserver/requesthandler.py
djangoquietrunserver/management/__init__.py
djangoquietrunserver/management/commands/__init__.py
djangoquietrunserver/management/commands/runserver--.py