Metadata-Version: 1.1
Name: django-quiet-runserver
Version: 0.2.0
Summary: Quieter runserver for Django
Home-page: https://bitbucket.org/tim_heap/django-quiet-runserver
Author: Tim Heap
Author-email: tim@timheap.me
License: UNKNOWN
Platform: UNKNOWN
Classifier: Environment :: Web Environment
Classifier: Intended Audience :: Developers
Classifier: Operating System :: OS Independent
Classifier: Programming Language :: Python
Classifier: Framework :: Django
